{
  "journal": "SIFIN",
  "extraction_time": "2025-07-11T14:08:28.918844",
  "manuscripts": [
    {
      "id": "M174160",
      "title": "Complex Discontinuities of $\\sqrt{\\text{Fredholm Determinants}}$ in the Volterra Stein-Stein Model",
      "status": "Under Review / Chase Referees",
      "url": "cgi-bin/main.plex?form_type=view_ms&j_id=16&ms_id=147228&ms_rev_no=0&ms_id_key=ftdpjeddPeq90CtAHY3aSTuA",
      "corresponding_editor": "N/A",
      "associate_editor": "Possama\u00ef",
      "submitted": "2025-03-13  09:24",
      "submission_date": "2025-03-13",
      "referees": [
        {
          "name": "Nicolas Privault #1",
          "email": "",
          "status": "Accepted",
          "invited_date": null,
          "due_date": null,
          "report_available": true
        },
        {
          "name": "Antoine Jacquier #2",
          "email": "",
          "status": "Accepted",
          "invited_date": null,
          "due_date": null,
          "report_available": true
        }
      ],
      "documents": {
        "pdf": null,
        "referee_reports": [],
        "cover_letter": null
      }
    },
    {
      "id": "M174727",
      "title": "Dynamic Mean-Variance Asset Allocation in General Incomplete Markets: A Nonlocal BSDE-Based Feedback Control Approach",
      "status": "Under Review / Chase Referees",
      "url": "cgi-bin/main.plex?form_type=view_ms&j_id=16&ms_id=147862&ms_rev_no=0&ms_id_key=ftdEFfz2UM5jT9qYmUeWwmyA",
      "corresponding_editor": "N/A",
      "associate_editor": "Possama\u00ef",
      "submitted": "2025-04-01  09:52",
      "submission_date": "2025-04-01",
      "referees": [
        {
          "name": "Camilo hernandez #1",
          "email": "",
          "status": "Accepted",
          "invited_date": null,
          "due_date": null,
          "report_available": true
        },
        {
          "name": "Qingmeng Wei #2",
          "email": "",
          "status": "Accepted",
          "invited_date": null,
          "due_date": null,
          "report_available": true
        }
      ],
      "documents": {
        "pdf": null,
        "referee_reports": [],
        "cover_letter": null
      }
    },
    {
      "id": "M175988",
      "title": "Numerical Analysis of a Particle System for the Calibrated Heston-Type Local Stochastic Volatility Model",
      "status": "Under Review",
      "url": "cgi-bin/main.plex?form_type=view_ms&j_id=16&ms_id=149254&ms_rev_no=0&ms_id_key=ftdFPcxb6vIbyMgivYTo6fA",
      "corresponding_editor": "N/A",
      "associate_editor": "Possama\u00ef",
      "submitted": "2025-05-19  15:13",
      "submission_date": "2025-05-19",
      "referees": [
        {
          "name": "Andreas Neuenkirch #1",
          "email": "",
          "status": "Accepted",
          "invited_date": null,
          "due_date": null,
          "report_available": true
        },
        {
          "name": "Aur\u00e9lien Alfonsi #2",
          "email": "",
          "status": "Accepted",
          "invited_date": null,
          "due_date": null,
          "report_available": true,
          "email_verification": {
            "verified": true,
            "emails_found": 2,
            "invitation_date": null,
            "last_verified": "2025-07-11T14:08:26.966177"
          }
        }
      ],
      "documents": {
        "pdf": null,
        "referee_reports": [],
        "cover_letter": null
      }
    },
    {
      "id": "M176140",
      "title": "Optimal Investment and Consumption Strategies with General Cost Structure under CRRA Utility",
      "status": "Under Review",
      "url": "cgi-bin/main.plex?form_type=view_ms&j_id=16&ms_id=149423&ms_rev_no=0&ms_id_key=ftdz9naeAnmWgxAVVH6TI1LXg",
      "corresponding_editor": "N/A",
      "associate_editor": "Possama\u00ef",
      "submitted": "2025-05-26  10:28",
      "submission_date": "2025-05-26",
      "referees": [
        {
          "name": "Xiaofei Shi #1",
          "email": "",
          "status": "Accepted",
          "invited_date": null,
          "due_date": null,
          "report_available": true
        },
        {
          "name": "Frank Seifried #2",
          "email": "",
          "status": "Accepted",
          "invited_date": null,
          "due_date": null,
          "report_available": true
        }
      ],
      "documents": {
        "pdf": null,
        "referee_reports": [],
        "cover_letter": null
      }
    }
  ],
  "changes": {
    "new_manuscripts": [
      {
        "id": "M176140",
        "title": "Optimal Investment and Consumption Strategies with General Cost Structure under CRRA Utility",
        "submitted": "2025-05-26  10:28"
      },
      {
        "id": "M174727",
        "title": "Dynamic Mean-Variance Asset Allocation in General Incomplete Markets: A Nonlocal BSDE-Based Feedback Control Approach",
        "submitted": "2025-04-01  09:52"
      },
      {
        "id": "M174160",
        "title": "Complex Discontinuities of $\\sqrt{\\text{Fredholm Determinants}}$ in the Volterra Stein-Stein Model",
        "submitted": "2025-03-13  09:24"
      },
      {
        "id": "M175988",
        "title": "Numerical Analysis of a Particle System for the Calibrated Heston-Type Local Stochastic Volatility Model",
        "submitted": "2025-05-19  15:13"
      }
    ],
    "status_changes": [],
    "new_reports": [],
    "new_referees": [],
    "overdue_reviews": [],
    "approaching_deadlines": []
  }
}